jsonmenu/__init__.py
jsonmenu/jsonmenu.py
jsonmenu-1.0.1.dist-info/LICENSE
jsonmenu-1.0.1.dist-info/METADATA
jsonmenu-1.0.1.dist-info/WHEEL
jsonmenu-1.0.1.dist-info/top_level.txt
jsonmenu-1.0.1.dist-info/RECORD
