Metadata-Version: 2.1
Name: jsonmenu
Version: 1.0.1
Summary: The easiest way to create interactive console menus in Python using JSON
Home-page: https://github.com/xavi-burgos99/jsonmenu
Author: Xavi Burgos
Author-email: xavi@dzin.es
License: MIT
Keywords: json menu console interactive python
Platform: UNKNOWN
Classifier: Programming Language :: Python :: 3
Classifier: License :: OSI Approved :: MIT License
Classifier: Operating System :: OS Independent
Requires-Python: >=3.6
License-File: LICENSE
